LICENSE
README.md
pyproject.toml
setup.py
src/repec/__init__.py
src/repec/database.py
src/repec/export_bib.py
src/repec/main.py
src/repec/misc.py
src/repec/network.py
src/repec/papers.py
src/repec/patch-journal-names.py
src/repec/redif.py
src/repec/remotes.py
src/repec/repec.py
src/repec/sanitize.py
src/repec/settings.py
src/repec.egg-info/PKG-INFO
src/repec.egg-info/SOURCES.txt
src/repec.egg-info/dependency_links.txt
src/repec.egg-info/entry_points.txt
src/repec.egg-info/requires.txt
src/repec.egg-info/top_level.txt