Metadata-Version: 2.1
Name: repec
Version: 0.0.1rc3
Summary: Download RePEc database
Author-email: Andrei Dubovik <chat@dubovik.eu>, Mingze Gao <adrian.gao@outlook.com>
License: GPLv3
Project-URL: homepage, https://github.com/mgao6767/repec
Classifier: Operating System :: OS Independent
Classifier: License :: OSI Approved :: GNU General Public License v3 (GPLv3)
Classifier: Programming Language :: Python :: 3.10
Classifier: Programming Language :: Python :: 3.11
Classifier: Intended Audience :: Financial and Insurance Industry
Classifier: Intended Audience :: Education
Classifier: Intended Audience :: Science/Research
Requires-Python: >=3.10
License-File: LICENSE
Requires-Dist: requests
Requires-Dist: lxml
Requires-Dist: cld2-cffi
Requires-Dist: html5lib
Requires-Dist: nameparser
Requires-Dist: titlecase
